{
  "_note": "Hand-curated seed list of DRs. Format: underlying -> [DR candidates]. Add/edit entries manually, then run scripts/dr/discover_drs.py to generate mapping.json. Use home-market tickers for the underlying, not a US ADR that's already directly investable (see universe.py's us_equity notes) — that's why Toyota is 7203.T (Tokyo) and ASML is ASML.AS (Amsterdam), not their US-listed tickers. ISSUER POLICY (added 2026-07-15): only include DRs issued by a Thai bank or a securities-firm subsidiary of a Thai bank -- KTB (Krungthai Bank, ticker suffix '80'), BLS (Bualuang Securities, subsidiary of Bangkok Bank, suffix '01'), and INVX (InnovestX Securities, subsidiary of SCBX/Siam Commercial Bank, suffix '23'). Do NOT add DRs issued by Yuanta Securities (Thailand) (suffix '19' -- subsidiary of Taiwan's Yuanta Financial Holdings, not a Thai bank) or KGI Securities (suffix '13' -- also Taiwan-affiliated). 32 candidates issued by those two were removed on 2026-07-15 for this reason.",
  "005930.KS": [
    {
      "dr_ticker": "SAMSUNG80.BK",
      "display_name": "Samsung Electronics",
      "underlying_exchange": "KR",
      "underlying_currency": "KRW",
      "ratio": 80
    }
  ],
  "0700.HK": [
    {
      "dr_ticker": "TENCENT80.BK",
      "display_name": "Tencent Holdings",
      "underlying_exchange": "HK",
      "underlying_currency": "HKD",
      "ratio": 100
    }
  ],
  "7203.T": [
    {
      "dr_ticker": "TOYOTA80.BK",
      "display_name": "Toyota Motor",
      "underlying_exchange": "JP",
      "underlying_currency": "JPY",
      "ratio": 100
    }
  ],
  "ASML.AS": [
    {
      "dr_ticker": "ASML01.BK",
      "display_name": "ASML Holding",
      "underlying_exchange": "NL",
      "underlying_currency": "EUR",
      "ratio": 1200
    }
  ],
  "9988.HK": [
    {
      "dr_ticker": "BABA80.BK",
      "display_name": "Alibaba Group",
      "underlying_exchange": "HK",
      "underlying_currency": "HKD",
      "ratio": 100
    }
  ],
  "9888.HK": [
    {
      "dr_ticker": "BIDU80.BK",
      "display_name": "Baidu",
      "underlying_exchange": "HK",
      "underlying_currency": "HKD",
      "ratio": 100
    }
  ],
  "9618.HK": [
    {
      "dr_ticker": "JD80.BK",
      "display_name": "JD.com",
      "underlying_exchange": "HK",
      "underlying_currency": "HKD",
      "ratio": 100
    }
  ],
  "3690.HK": [
    {
      "dr_ticker": "MEITUAN80.BK",
      "display_name": "Meituan",
      "underlying_exchange": "HK",
      "underlying_currency": "HKD",
      "ratio": 100
    }
  ],
  "9999.HK": [
    {
      "dr_ticker": "NETEASE80.BK",
      "display_name": "NetEase",
      "underlying_exchange": "HK",
      "underlying_currency": "HKD",
      "ratio": 100
    }
  ],
  "1211.HK": [
    {
      "dr_ticker": "BYDCOM80.BK",
      "display_name": "BYD Company",
      "underlying_exchange": "HK",
      "underlying_currency": "HKD",
      "ratio": 1000
    }
  ],
  "1810.HK": [
    {
      "dr_ticker": "XIAOMI80.BK",
      "display_name": "Xiaomi",
      "underlying_exchange": "HK",
      "underlying_currency": "HKD",
      "ratio": 10
    }
  ],
  "2899.HK": [
    {
      "dr_ticker": "ZIJIN80.BK",
      "display_name": "Zijin Mining",
      "underlying_exchange": "HK",
      "underlying_currency": "HKD",
      "ratio": 10
    }
  ],
  "1024.HK": [
    {
      "dr_ticker": "KUAISH80.BK",
      "display_name": "Kuaishou Technology",
      "underlying_exchange": "HK",
      "underlying_currency": "HKD",
      "ratio": 100
    }
  ],
  "0175.HK": [
    {
      "dr_ticker": "GEELY80.BK",
      "display_name": "Geely Automobile",
      "underlying_exchange": "HK",
      "underlying_currency": "HKD",
      "ratio": 10
    }
  ],
  "3968.HK": [
    {
      "dr_ticker": "CMBANK23.BK",
      "display_name": "China Merchants Bank",
      "underlying_exchange": "HK",
      "underlying_currency": "HKD",
      "ratio": 90
    }
  ],
  "0857.HK": [
    {
      "dr_ticker": "PETROCN80.BK",
      "display_name": "PetroChina",
      "underlying_exchange": "HK",
      "underlying_currency": "HKD",
      "ratio": 10
    }
  ],
  "9992.HK": [
    {
      "dr_ticker": "POPMART80.BK",
      "display_name": "Pop Mart",
      "underlying_exchange": "HK",
      "underlying_currency": "HKD",
      "ratio": 100
    }
  ],
  "0020.HK": [
    {
      "dr_ticker": "SENSE23.BK",
      "display_name": "SenseTime",
      "underlying_exchange": "HK",
      "underlying_currency": "HKD",
      "ratio": 4
    }
  ],
  "1347.HK": [
    {
      "dr_ticker": "HUAHONG23.BK",
      "display_name": "Hua Hong Semiconductor",
      "underlying_exchange": "HK",
      "underlying_currency": "HKD",
      "ratio": 999
    }
  ],
  "9660.HK": [
    {
      "dr_ticker": "HORIZON23.BK",
      "display_name": "Horizon Robotics",
      "underlying_exchange": "HK",
      "underlying_currency": "HKD",
      "ratio": 16
    }
  ],
  "3888.HK": [
    {
      "dr_ticker": "KINGSOFT23.BK",
      "display_name": "Kingsoft Corporation",
      "underlying_exchange": "HK",
      "underlying_currency": "HKD",
      "ratio": 60
    }
  ],
  "9880.HK": [
    {
      "dr_ticker": "UBTECH23.BK",
      "display_name": "UBTECH Robotics",
      "underlying_exchange": "HK",
      "underlying_currency": "HKD",
      "ratio": 250
    }
  ],
  "9633.HK": [
    {
      "dr_ticker": "NONGFU80.BK",
      "display_name": "Nongfu Spring",
      "underlying_exchange": "HK",
      "underlying_currency": "HKD",
      "ratio": 100
    }
  ],
  "3750.HK": [
    {
      "dr_ticker": "CATL80.BK",
      "display_name": "CATL",
      "underlying_exchange": "HK",
      "underlying_currency": "HKD",
      "ratio": 100
    }
  ],
  "6758.T": [
    {
      "dr_ticker": "SONY80.BK",
      "display_name": "Sony Group",
      "underlying_exchange": "JP",
      "underlying_currency": "JPY",
      "ratio": 200
    }
  ],
  "9984.T": [
    {
      "dr_ticker": "SOFTBANK23.BK",
      "display_name": "SoftBank Group",
      "underlying_exchange": "JP",
      "underlying_currency": "JPY",
      "ratio": 527.5
    }
  ],
  "8035.T": [
    {
      "dr_ticker": "TEL23.BK",
      "display_name": "Tokyo Electron",
      "underlying_exchange": "JP",
      "underlying_currency": "JPY",
      "ratio": 2710
    }
  ],
  "6861.T": [
    {
      "dr_ticker": "KEYENCE23.BK",
      "display_name": "Keyence Corp",
      "underlying_exchange": "JP",
      "underlying_currency": "JPY",
      "ratio": 5650
    }
  ],
  "9983.T": [
    {
      "dr_ticker": "UNIQLO80.BK",
      "display_name": "Fast Retailing (Uniqlo)",
      "underlying_exchange": "JP",
      "underlying_currency": "JPY",
      "ratio": 1000
    }
  ],
  "8136.T": [
    {
      "dr_ticker": "SANRIO23.BK",
      "display_name": "Sanrio",
      "underlying_exchange": "JP",
      "underlying_currency": "JPY",
      "ratio": 136
    }
  ],
  "3563.T": [
    {
      "dr_ticker": "SUSHI23.BK",
      "display_name": "Food & Life Companies (Sushiro)",
      "underlying_exchange": "JP",
      "underlying_currency": "JPY",
      "ratio": 332
    }
  ],
  "RMS.PA": [
    {
      "dr_ticker": "HERMES80.BK",
      "display_name": "Hermès International",
      "underlying_exchange": "FR",
      "underlying_currency": "EUR",
      "ratio": 10000
    }
  ],
  "OR.PA": [
    {
      "dr_ticker": "LOREAL80.BK",
      "display_name": "L'Oréal",
      "underlying_exchange": "FR",
      "underlying_currency": "EUR",
      "ratio": 10000
    }
  ],
  "MC.PA": [
    {
      "dr_ticker": "LVMH01.BK",
      "display_name": "LVMH",
      "underlying_exchange": "FR",
      "underlying_currency": "EUR",
      "ratio": 1600
    }
  ],
  "NOVO-B.CO": [
    {
      "dr_ticker": "NOVOB80.BK",
      "display_name": "Novo Nordisk",
      "underlying_exchange": "DK",
      "underlying_currency": "DKK",
      "ratio": 1000
    }
  ],
  "SAN.PA": [
    {
      "dr_ticker": "SANOFI80.BK",
      "display_name": "Sanofi",
      "underlying_exchange": "FR",
      "underlying_currency": "EUR",
      "ratio": 1000
    }
  ],
  "RACE.MI": [
    {
      "dr_ticker": "FERRARI80.BK",
      "display_name": "Ferrari",
      "underlying_exchange": "IT",
      "underlying_currency": "EUR",
      "ratio": 10000
    }
  ],
  "2330.TW": [
    {
      "dr_ticker": "TSMC80.BK",
      "display_name": "Taiwan Semiconductor (TSMC)",
      "underlying_exchange": "TW",
      "underlying_currency": "TWD",
      "ratio": 999
    }
  ],
  "Z74.SI": [
    {
      "dr_ticker": "SINGTEL80.BK",
      "display_name": "Singtel",
      "underlying_exchange": "SG",
      "underlying_currency": "SGD",
      "ratio": 10
    }
  ]
}